Metadata-Version: 2.1
Name: matchup-ir
Version: 0.4.0
Summary: A IR simple library.
Home-page: https://github.com/marcosfpr/match_up_lib
Author: Marcos Pontes
Author-email: marcos.rezende@aluno.ufop.com
License: UNKNOWN
Platform: UNKNOWN
Classifier: Programming Language :: Python :: 3
Classifier: License :: OSI Approved :: MIT License
Classifier: Operating System :: OS Independent
Requires-Python: >=3.7
